DescribeLinearModel/Describelinearmodel.py
DescribeLinearModel/Describelinearmodel_unittest.py
DescribeLinearModel/__init__.py
DescribeLinearModel-1.0.1.dist-info/METADATA
DescribeLinearModel-1.0.1.dist-info/WHEEL
DescribeLinearModel-1.0.1.dist-info/top_level.txt
DescribeLinearModel-1.0.1.dist-info/RECORD
