Metadata-Version: 2.1
Name: DescribeLinearModel
Version: 1.0.1
Summary: class for calculating and visualizing a regression line
Home-page: UNKNOWN
Author: Eugen Iftimoaie
Author-email: UNKNOWN
License: UNKNOWN
Platform: UNKNOWN
